loop_tool_py.cpython-310-x86_64-linux-gnu.so
libloop_tool.so
loop_tool/nn.py
loop_tool/ui.py
loop_tool/__init__.py
loop_tool-0.1.0.dist-info/LICENSE
loop_tool-0.1.0.dist-info/METADATA
loop_tool-0.1.0.dist-info/top_level.txt
loop_tool-0.1.0.dist-info/RECORD
loop_tool-0.1.0.dist-info/WHEEL
