Metadata-Version: 2.1
Name: loop-tool
Version: 0.1.0
Summary: A lightweight IR for dense linear algebra
Home-page: https://github.com/facebookresearch/loop_tool
Author: Bram Wasti
Author-email: bwasti@fb.com
License: UNKNOWN
Platform: UNKNOWN
License-File: LICENSE
